{
  "posts": [
    {
      "id": 1,
      "title": "json-server",
      "author": "typicode"
    }
  ],
  "comments": [
    {
      "id": 1,
      "body": "some comment",
      "postId": 1
    }
  ],
  "signupUsers": [
    {
      "firstname": "Sanskriti",
      "lastname": "Khandelwal",
      "email": "root@123",
      "password": "123456",
      "confirmPassword": "123456",
      "id": 1
    },
    {
      "firstname": "Sanskar",
      "lastname": "khandelwal",
      "email": "root@1234",
      "password": "123456",
      "confirmPassword": "123456",
      "id": 2
    }
  ],
  "contact": []
}